{
  "students": [
    {
      "id": "2",
      "name": "Thế Anh 36",
      "address": "Thanh Hoá",
      "points": 6
    },
    {
      "id": "4",
      "name": "trần ngọc đức 36",
      "address": "Ninh Bình",
      "points": 7
    },
    {
      "id": "5",
      "name": "TRẦN THẾ ANH",
      "address": "Ninh Bình",
      "points": 5
    },
    {
      "name": "trần ngọc đức",
      "address": "Mỹ Đình- Hà Nội",
      "points": 6,
      "id": "7"
    },
    {
      "name": "trần ngọc đức",
      "address": "Ninh Bình",
      "points": 9,
      "id": "8"
    },
    {
      "name": "TRẦN THẾ ANH",
      "address": "Ninh Bình",
      "points": 10,
      "id": "9"
    },
    {
      "name": "trần ngọc đức",
      "address": "Mỹ Đình- Hà Nội",
      "points": 2,
      "id": "10"
    },
    {
      "name": "Alan Tran",
      "address": "Thanh Hoá",
      "points": 7,
      "id": "11"
    },
    {
      "name": "trần thế anh",
      "address": "Thanh Hoá 33",
      "points": 9,
      "id": "12"
    }
  ]
}